README.md
setup.py
PyML/__init__.py
PyML/main.py
PyML/parser.py
PyML/window.py
PyML.egg-info/PKG-INFO
PyML.egg-info/SOURCES.txt
PyML.egg-info/dependency_links.txt
PyML.egg-info/requires.txt
PyML.egg-info/top_level.txt
PyML/utils/__init__.py
PyML/utils/table.py