Metadata-Version: 2.1
Name: PyML
Version: 0.0.5
Summary: A python HTML builder library.
Home-page: https://github.com/ArjixWasTaken/PyML
Author: Arjix
Author-email: arjixg53@gmail.com
License: UNKNOWN
Keywords: html,html builder
Platform: UNKNOWN
Classifier: Programming Language :: Python :: 3
Classifier: License :: OSI Approved :: MIT License
Classifier: Operating System :: OS Independent
Requires-Python: >=3.6
